<annotation verified="yes">
	<folder>DataMask</folder>
	<filename>467_day_outside.JPG</filename>
	<path>F:\Phan mem\Hoc Tap\May Hoc\CS114.L21.KHCL\FinalProject\Data\DataMask\467_day_outside.JPG</path>
	<source>
		<database>Unknown</database>
	</source>
	<size>
		<width>3264</width>
		<height>2448</height>
		<depth>3</depth>
	</size>
	<segmented>0</segmented>
	<object>
		<name>hole</name>
		<pose>Unspecified</pose>
		<truncated>1</truncated>
		<difficult>0</difficult>
		<bndbox>
			<xmin>1100</xmin>
			<ymin>2283</ymin>
			<xmax>1481</xmax>
			<ymax>2448</ymax>
		</bndbox>
	</object>
	<object>
		<name>hole</name>
		<pose>Unspecified</pose>
		<truncated>0</truncated>
		<difficult>0</difficult>
		<bndbox>
			<xmin>1178</xmin>
			<ymin>2117</ymin>
			<xmax>1478</xmax>
			<ymax>2268</ymax>
		</bndbox>
	</object>
	<object>
		<name>hole</name>
		<pose>Unspecified</pose>
		<truncated>0</truncated>
		<difficult>0</difficult>
		<bndbox>
			<xmin>1496</xmin>
			<ymin>1758</ymin>
			<xmax>1903</xmax>
			<ymax>1905</ymax>
		</bndbox>
	</object>
	<object>
		<name>hole</name>
		<pose>Unspecified</pose>
		<truncated>0</truncated>
		<difficult>0</difficult>
		<bndbox>
			<xmin>1477</xmin>
			<ymin>1690</ymin>
			<xmax>1709</xmax>
			<ymax>1749</ymax>
		</bndbox>
	</object>
</annotation>
