<annotation>
	<folder>DataMask</folder>
	<filename>1012_day_outside.jpg</filename>
	<path>D:\AI\1\DataMask\1012_day_outside.jpg</path>
	<source>
		<database>Unknown</database>
	</source>
	<size>
		<width>2016</width>
		<height>4032</height>
		<depth>3</depth>
	</size>
	<segmented>0</segmented>
	<object>
		<name>hole</name>
		<pose>Unspecified</pose>
		<truncated>0</truncated>
		<difficult>0</difficult>
		<bndbox>
			<xmin>1512</xmin>
			<ymin>1569</ymin>
			<xmax>1748</xmax>
			<ymax>1619</ymax>
		</bndbox>
	</object>
	<object>
		<name>hole</name>
		<pose>Unspecified</pose>
		<truncated>0</truncated>
		<difficult>0</difficult>
		<bndbox>
			<xmin>1303</xmin>
			<ymin>1622</ymin>
			<xmax>1427</xmax>
			<ymax>1645</ymax>
		</bndbox>
	</object>
	<object>
		<name>hole</name>
		<pose>Unspecified</pose>
		<truncated>0</truncated>
		<difficult>0</difficult>
		<bndbox>
			<xmin>909</xmin>
			<ymin>1757</ymin>
			<xmax>1055</xmax>
			<ymax>1803</ymax>
		</bndbox>
	</object>
	<object>
		<name>hole</name>
		<pose>Unspecified</pose>
		<truncated>0</truncated>
		<difficult>0</difficult>
		<bndbox>
			<xmin>898</xmin>
			<ymin>1694</ymin>
			<xmax>1059</xmax>
			<ymax>1732</ymax>
		</bndbox>
	</object>
	<object>
		<name>hole</name>
		<pose>Unspecified</pose>
		<truncated>0</truncated>
		<difficult>0</difficult>
		<bndbox>
			<xmin>564</xmin>
			<ymin>1885</ymin>
			<xmax>1170</xmax>
			<ymax>2009</ymax>
		</bndbox>
	</object>
</annotation>
