<annotation verified="yes">
	<folder>TakeData</folder>
	<filename>494_day_outside.jpg</filename>
	<path>E:\Studies\Personal\TakeData\494_day_outside.jpg</path>
	<source>
		<database>Unknown</database>
	</source>
	<size>
		<width>2016</width>
		<height>4032</height>
		<depth>3</depth>
	</size>
	<segmented>0</segmented>
	<object>
		<name>hole</name>
		<pose>Unspecified</pose>
		<truncated>0</truncated>
		<difficult>0</difficult>
		<bndbox>
			<xmin>710</xmin>
			<ymin>2488</ymin>
			<xmax>1158</xmax>
			<ymax>2720</ymax>
		</bndbox>
	</object>
	<object>
		<name>hole</name>
		<pose>Unspecified</pose>
		<truncated>0</truncated>
		<difficult>0</difficult>
		<bndbox>
			<xmin>686</xmin>
			<ymin>3092</ymin>
			<xmax>1250</xmax>
			<ymax>3468</ymax>
		</bndbox>
	</object>
</annotation>
