<annotation>
	<folder>DataMask</folder>
	<filename>901_day_outside.jpg</filename>
	<path>D:\AI\1\DataMask\901_day_outside.jpg</path>
	<source>
		<database>Unknown</database>
	</source>
	<size>
		<width>2016</width>
		<height>4032</height>
		<depth>3</depth>
	</size>
	<segmented>0</segmented>
	<object>
		<name>hole</name>
		<pose>Unspecified</pose>
		<truncated>0</truncated>
		<difficult>0</difficult>
		<bndbox>
			<xmin>309</xmin>
			<ymin>1940</ymin>
			<xmax>874</xmax>
			<ymax>2169</ymax>
		</bndbox>
	</object>
	<object>
		<name>hole</name>
		<pose>Unspecified</pose>
		<truncated>0</truncated>
		<difficult>0</difficult>
		<bndbox>
			<xmin>1055</xmin>
			<ymin>1945</ymin>
			<xmax>1570</xmax>
			<ymax>2149</ymax>
		</bndbox>
	</object>
	<object>
		<name>hole</name>
		<pose>Unspecified</pose>
		<truncated>0</truncated>
		<difficult>0</difficult>
		<bndbox>
			<xmin>101</xmin>
			<ymin>1570</ymin>
			<xmax>380</xmax>
			<ymax>1639</ymax>
		</bndbox>
	</object>
	<object>
		<name>hole</name>
		<pose>Unspecified</pose>
		<truncated>0</truncated>
		<difficult>0</difficult>
		<bndbox>
			<xmin>9</xmin>
			<ymin>1707</ymin>
			<xmax>675</xmax>
			<ymax>1850</ymax>
		</bndbox>
	</object>
	<object>
		<name>hole</name>
		<pose>Unspecified</pose>
		<truncated>0</truncated>
		<difficult>0</difficult>
		<bndbox>
			<xmin>915</xmin>
			<ymin>1556</ymin>
			<xmax>1097</xmax>
			<ymax>1597</ymax>
		</bndbox>
	</object>
	<object>
		<name>hole</name>
		<pose>Unspecified</pose>
		<truncated>0</truncated>
		<difficult>0</difficult>
		<bndbox>
			<xmin>137</xmin>
			<ymin>2886</ymin>
			<xmax>1325</xmax>
			<ymax>3977</ymax>
		</bndbox>
	</object>
	<object>
		<name>hole</name>
		<pose>Unspecified</pose>
		<truncated>0</truncated>
		<difficult>0</difficult>
		<bndbox>
			<xmin>359</xmin>
			<ymin>2332</ymin>
			<xmax>1334</xmax>
			<ymax>2838</ymax>
		</bndbox>
	</object>
</annotation>
